cubapy/__init__.py
cubapy/line.py
cubapy/plot.py
cubapy/tet.py
cubapy/tri.py
cubapy-0.0.2.data/data/README/README.md
cubapy-0.0.2.data/data/licenses/MIT
cubapy-0.0.2.dist-info/LICENSE
cubapy-0.0.2.dist-info/METADATA
cubapy-0.0.2.dist-info/WHEEL
cubapy-0.0.2.dist-info/top_level.txt
cubapy-0.0.2.dist-info/RECORD
